{"nodes": [{"id": "c_users_mcn_dev_sdr_growth_engine_discovery_base_py", "label": "base.py", "file_type": "code", "source_file": "C:\\Users\\MCN\\Dev\\SDR\\growth_engine\\discovery\\base.py", "source_location": "L1"}, {"id": "discovery_base_discoveryadapter", "label": "DiscoveryAdapter", "file_type": "code", "source_file": "C:\\Users\\MCN\\Dev\\SDR\\growth_engine\\discovery\\base.py", "source_location": "L9"}, {"id": "abc", "label": "ABC", "file_type": "code", "source_file": "", "source_location": ""}, {"id": "discovery_base_discover", "label": "discover()", "file_type": "code", "source_file": "C:\\Users\\MCN\\Dev\\SDR\\growth_engine\\discovery\\base.py", "source_location": "L14"}], "edges": [{"source": "c_users_mcn_dev_sdr_growth_engine_discovery_base_py", "target": "abc", "relation": "imports_from", "context": "import", "confidence": "EXTRACTED", "source_file": "C:\\Users\\MCN\\Dev\\SDR\\growth_engine\\discovery\\base.py", "source_location": "L3", "weight": 1.0}, {"source": "c_users_mcn_dev_sdr_growth_engine_discovery_base_py", "target": "collections_abc", "relation": "imports_from", "context": "import", "confidence": "EXTRACTED", "source_file": "C:\\Users\\MCN\\Dev\\SDR\\growth_engine\\discovery\\base.py", "source_location": "L4", "weight": 1.0}, {"source": "c_users_mcn_dev_sdr_growth_engine_discovery_base_py", "target": "growth_engine_models", "relation": "imports_from", "context": "import", "confidence": "EXTRACTED", "source_file": "C:\\Users\\MCN\\Dev\\SDR\\growth_engine\\discovery\\base.py", "source_location": "L6", "weight": 1.0}, {"source": "c_users_mcn_dev_sdr_growth_engine_discovery_base_py", "target": "discovery_base_discoveryadapter", "relation": "contains", "confidence": "EXTRACTED", "source_file": "C:\\Users\\MCN\\Dev\\SDR\\growth_engine\\discovery\\base.py", "source_location": "L9", "weight": 1.0}, {"source": "discovery_base_discoveryadapter", "target": "abc", "relation": "inherits", "confidence": "EXTRACTED", "source_file": "C:\\Users\\MCN\\Dev\\SDR\\growth_engine\\discovery\\base.py", "source_location": "L9", "weight": 1.0}, {"source": "c_users_mcn_dev_sdr_growth_engine_discovery_base_py", "target": "discovery_base_discover", "relation": "contains", "confidence": "EXTRACTED", "source_file": "C:\\Users\\MCN\\Dev\\SDR\\growth_engine\\discovery\\base.py", "source_location": "L14", "weight": 1.0}], "raw_calls": []}