{"nodes": [{"id": "c_users_mcn_dev_sdr_growth_engine_web_forms_py", "label": "forms.py", "file_type": "code", "source_file": "C:\\Users\\MCN\\Dev\\SDR\\growth_engine_web\\forms.py", "source_location": "L1"}, {"id": "growth_engine_web_forms_sourceresearchform", "label": "SourceResearchForm", "file_type": "code", "source_file": "C:\\Users\\MCN\\Dev\\SDR\\growth_engine_web\\forms.py", "source_location": "L18"}, {"id": "growth_engine_web_forms_sourceresearchform_clean_business_name", "label": ".clean_business_name()", "file_type": "code", "source_file": "C:\\Users\\MCN\\Dev\\SDR\\growth_engine_web\\forms.py", "source_location": "L41"}, {"id": "growth_engine_web_forms_sourceresearchform_clean_website", "label": ".clean_website()", "file_type": "code", "source_file": "C:\\Users\\MCN\\Dev\\SDR\\growth_engine_web\\forms.py", "source_location": "L44"}, {"id": "growth_engine_web_forms_profilesectionform", "label": "ProfileSectionForm", "file_type": "code", "source_file": "C:\\Users\\MCN\\Dev\\SDR\\growth_engine_web\\forms.py", "source_location": "L48"}, {"id": "growth_engine_web_forms_profilesectionform_init", "label": ".__init__()", "file_type": "code", "source_file": "C:\\Users\\MCN\\Dev\\SDR\\growth_engine_web\\forms.py", "source_location": "L49"}, {"id": "growth_engine_web_forms_profilesectionform_cleaned_partial_values", "label": ".cleaned_partial_values()", "file_type": "code", "source_file": "C:\\Users\\MCN\\Dev\\SDR\\growth_engine_web\\forms.py", "source_location": "L67"}, {"id": "growth_engine_web_forms_postsaverequestform", "label": "PostSaveRequestForm", "file_type": "code", "source_file": "C:\\Users\\MCN\\Dev\\SDR\\growth_engine_web\\forms.py", "source_location": "L74"}, {"id": "growth_engine_web_forms_postsaverequestform_clean_requested_data", "label": ".clean_requested_data()", "file_type": "code", "source_file": "C:\\Users\\MCN\\Dev\\SDR\\growth_engine_web\\forms.py", "source_location": "L92"}, {"id": "growth_engine_web_forms_postsaverequestform_clean_notes", "label": ".clean_notes()", "file_type": "code", "source_file": "C:\\Users\\MCN\\Dev\\SDR\\growth_engine_web\\forms.py", "source_location": "L97"}, {"id": "growth_engine_web_forms_socialcontentrequestform", "label": "SocialContentRequestForm", "file_type": "code", "source_file": "C:\\Users\\MCN\\Dev\\SDR\\growth_engine_web\\forms.py", "source_location": "L101"}, {"id": "growth_engine_web_forms_socialcontentrequestform_clean_campaign_goal", "label": ".clean_campaign_goal()", "file_type": "code", "source_file": "C:\\Users\\MCN\\Dev\\SDR\\growth_engine_web\\forms.py", "source_location": "L142"}, {"id": "growth_engine_web_forms_socialcontentrequestform_clean_channels", "label": ".clean_channels()", "file_type": "code", "source_file": "C:\\Users\\MCN\\Dev\\SDR\\growth_engine_web\\forms.py", "source_location": "L145"}, {"id": "growth_engine_web_forms_socialcontentrequestform_clean_notes", "label": ".clean_notes()", "file_type": "code", "source_file": "C:\\Users\\MCN\\Dev\\SDR\\growth_engine_web\\forms.py", "source_location": "L152"}, {"id": "growth_engine_web_forms_socialcontentrequestform_clean_delivery_email", "label": ".clean_delivery_email()", "file_type": "code", "source_file": "C:\\Users\\MCN\\Dev\\SDR\\growth_engine_web\\forms.py", "source_location": "L155"}], "edges": [{"source": "c_users_mcn_dev_sdr_growth_engine_web_forms_py", "target": "django", "relation": "imports_from", "context": "import", "confidence": "EXTRACTED", "source_file": "C:\\Users\\MCN\\Dev\\SDR\\growth_engine_web\\forms.py", "source_location": "L3", "weight": 1.0}, {"source": "c_users_mcn_dev_sdr_growth_engine_web_forms_py", "target": "growth_engine_models", "relation": "imports_from", "context": "import", "confidence": "EXTRACTED", "source_file": "C:\\Users\\MCN\\Dev\\SDR\\growth_engine_web\\forms.py", "source_location": "L5", "weight": 1.0}, {"source": "c_users_mcn_dev_sdr_growth_engine_web_forms_py", "target": "growth_engine_profile_flow", "relation": "imports_from", "context": "import", "confidence": "EXTRACTED", "source_file": "C:\\Users\\MCN\\Dev\\SDR\\growth_engine_web\\forms.py", "source_location": "L6", "weight": 1.0}, {"source": "c_users_mcn_dev_sdr_growth_engine_web_forms_py", "target": "growth_engine_utils", "relation": "imports_from", "context": "import", "confidence": "EXTRACTED", "source_file": "C:\\Users\\MCN\\Dev\\SDR\\growth_engine_web\\forms.py", "source_location": "L15", "weight": 1.0}, {"source": "c_users_mcn_dev_sdr_growth_engine_web_forms_py", "target": "growth_engine_web_forms_sourceresearchform", "relation": "contains", "confidence": "EXTRACTED", "source_file": "C:\\Users\\MCN\\Dev\\SDR\\growth_engine_web\\forms.py", "source_location": "L18", "weight": 1.0}, {"source": "growth_engine_web_forms_sourceresearchform", "target": "growth_engine_web_forms_sourceresearchform_clean_business_name", "relation": "method", "confidence": "EXTRACTED", "source_file": "C:\\Users\\MCN\\Dev\\SDR\\growth_engine_web\\forms.py", "source_location": "L41", "weight": 1.0}, {"source": "growth_engine_web_forms_sourceresearchform", "target": "growth_engine_web_forms_sourceresearchform_clean_website", "relation": "method", "confidence": "EXTRACTED", "source_file": "C:\\Users\\MCN\\Dev\\SDR\\growth_engine_web\\forms.py", "source_location": "L44", "weight": 1.0}, {"source": "c_users_mcn_dev_sdr_growth_engine_web_forms_py", "target": "growth_engine_web_forms_profilesectionform", "relation": "contains", "confidence": "EXTRACTED", "source_file": "C:\\Users\\MCN\\Dev\\SDR\\growth_engine_web\\forms.py", "source_location": "L48", "weight": 1.0}, {"source": "growth_engine_web_forms_profilesectionform", "target": "growth_engine_web_forms_profilesectionform_init", "relation": "method", "confidence": "EXTRACTED", "source_file": "C:\\Users\\MCN\\Dev\\SDR\\growth_engine_web\\forms.py", "source_location": "L49", "weight": 1.0}, {"source": "growth_engine_web_forms_profilesectionform", "target": "growth_engine_web_forms_profilesectionform_cleaned_partial_values", "relation": "method", "confidence": "EXTRACTED", "source_file": "C:\\Users\\MCN\\Dev\\SDR\\growth_engine_web\\forms.py", "source_location": "L67", "weight": 1.0}, {"source": "c_users_mcn_dev_sdr_growth_engine_web_forms_py", "target": "growth_engine_web_forms_postsaverequestform", "relation": "contains", "confidence": "EXTRACTED", "source_file": "C:\\Users\\MCN\\Dev\\SDR\\growth_engine_web\\forms.py", "source_location": "L74", "weight": 1.0}, {"source": "growth_engine_web_forms_postsaverequestform", "target": "growth_engine_web_forms_postsaverequestform_clean_requested_data", "relation": "method", "confidence": "EXTRACTED", "source_file": "C:\\Users\\MCN\\Dev\\SDR\\growth_engine_web\\forms.py", "source_location": "L92", "weight": 1.0}, {"source": "growth_engine_web_forms_postsaverequestform", "target": "growth_engine_web_forms_postsaverequestform_clean_notes", "relation": "method", "confidence": "EXTRACTED", "source_file": "C:\\Users\\MCN\\Dev\\SDR\\growth_engine_web\\forms.py", "source_location": "L97", "weight": 1.0}, {"source": "c_users_mcn_dev_sdr_growth_engine_web_forms_py", "target": "growth_engine_web_forms_socialcontentrequestform", "relation": "contains", "confidence": "EXTRACTED", "source_file": "C:\\Users\\MCN\\Dev\\SDR\\growth_engine_web\\forms.py", "source_location": "L101", "weight": 1.0}, {"source": "growth_engine_web_forms_socialcontentrequestform", "target": "growth_engine_web_forms_socialcontentrequestform_clean_campaign_goal", "relation": "method", "confidence": "EXTRACTED", "source_file": "C:\\Users\\MCN\\Dev\\SDR\\growth_engine_web\\forms.py", "source_location": "L142", "weight": 1.0}, {"source": "growth_engine_web_forms_socialcontentrequestform", "target": "growth_engine_web_forms_socialcontentrequestform_clean_channels", "relation": "method", "confidence": "EXTRACTED", "source_file": "C:\\Users\\MCN\\Dev\\SDR\\growth_engine_web\\forms.py", "source_location": "L145", "weight": 1.0}, {"source": "growth_engine_web_forms_socialcontentrequestform", "target": "growth_engine_web_forms_socialcontentrequestform_clean_notes", "relation": "method", "confidence": "EXTRACTED", "source_file": "C:\\Users\\MCN\\Dev\\SDR\\growth_engine_web\\forms.py", "source_location": "L152", "weight": 1.0}, {"source": "growth_engine_web_forms_socialcontentrequestform", "target": "growth_engine_web_forms_socialcontentrequestform_clean_delivery_email", "relation": "method", "confidence": "EXTRACTED", "source_file": "C:\\Users\\MCN\\Dev\\SDR\\growth_engine_web\\forms.py", "source_location": "L155", "weight": 1.0}], "raw_calls": [{"caller_nid": "growth_engine_web_forms_sourceresearchform_clean_business_name", "callee": "normalize_whitespace", "is_member_call": false, "source_file": "C:\\Users\\MCN\\Dev\\SDR\\growth_engine_web\\forms.py", "source_location": "L42"}, {"caller_nid": "growth_engine_web_forms_sourceresearchform_clean_website", "callee": "normalize_whitespace", "is_member_call": false, "source_file": "C:\\Users\\MCN\\Dev\\SDR\\growth_engine_web\\forms.py", "source_location": "L45"}, {"caller_nid": "growth_engine_web_forms_profilesectionform_init", "callee": "super", "is_member_call": false, "source_file": "C:\\Users\\MCN\\Dev\\SDR\\growth_engine_web\\forms.py", "source_location": "L50"}, {"caller_nid": "growth_engine_web_forms_profilesectionform_init", "callee": "TextInput", "is_member_call": true, "source_file": "C:\\Users\\MCN\\Dev\\SDR\\growth_engine_web\\forms.py", "source_location": "L53"}, {"caller_nid": "growth_engine_web_forms_profilesectionform_init", "callee": "Textarea", "is_member_call": true, "source_file": "C:\\Users\\MCN\\Dev\\SDR\\growth_engine_web\\forms.py", "source_location": "L56"}, {"caller_nid": "growth_engine_web_forms_profilesectionform_init", "callee": "Textarea", "is_member_call": true, "source_file": "C:\\Users\\MCN\\Dev\\SDR\\growth_engine_web\\forms.py", "source_location": "L58"}, {"caller_nid": "growth_engine_web_forms_profilesectionform_init", "callee": "CharField", "is_member_call": true, "source_file": "C:\\Users\\MCN\\Dev\\SDR\\growth_engine_web\\forms.py", "source_location": "L60"}, {"caller_nid": "growth_engine_web_forms_profilesectionform_cleaned_partial_values", "callee": "coerce_field_value", "is_member_call": false, "source_file": "C:\\Users\\MCN\\Dev\\SDR\\growth_engine_web\\forms.py", "source_location": "L69"}, {"caller_nid": "growth_engine_web_forms_postsaverequestform_clean_requested_data", "callee": "clean_requested_modes", "is_member_call": false, "source_file": "C:\\Users\\MCN\\Dev\\SDR\\growth_engine_web\\forms.py", "source_location": "L93"}, {"caller_nid": "growth_engine_web_forms_postsaverequestform_clean_requested_data", "callee": "list", "is_member_call": false, "source_file": "C:\\Users\\MCN\\Dev\\SDR\\growth_engine_web\\forms.py", "source_location": "L94"}, {"caller_nid": "growth_engine_web_forms_postsaverequestform_clean_requested_data", "callee": "get", "is_member_call": true, "source_file": "C:\\Users\\MCN\\Dev\\SDR\\growth_engine_web\\forms.py", "source_location": "L94"}, {"caller_nid": "growth_engine_web_forms_postsaverequestform_clean_notes", "callee": "normalize_whitespace", "is_member_call": false, "source_file": "C:\\Users\\MCN\\Dev\\SDR\\growth_engine_web\\forms.py", "source_location": "L98"}, {"caller_nid": "growth_engine_web_forms_postsaverequestform_clean_notes", "callee": "get", "is_member_call": true, "source_file": "C:\\Users\\MCN\\Dev\\SDR\\growth_engine_web\\forms.py", "source_location": "L98"}, {"caller_nid": "growth_engine_web_forms_socialcontentrequestform_clean_campaign_goal", "callee": "normalize_whitespace", "is_member_call": false, "source_file": "C:\\Users\\MCN\\Dev\\SDR\\growth_engine_web\\forms.py", "source_location": "L143"}, {"caller_nid": "growth_engine_web_forms_socialcontentrequestform_clean_campaign_goal", "callee": "get", "is_member_call": true, "source_file": "C:\\Users\\MCN\\Dev\\SDR\\growth_engine_web\\forms.py", "source_location": "L143"}, {"caller_nid": "growth_engine_web_forms_socialcontentrequestform_clean_channels", "callee": "list", "is_member_call": false, "source_file": "C:\\Users\\MCN\\Dev\\SDR\\growth_engine_web\\forms.py", "source_location": "L147"}, {"caller_nid": "growth_engine_web_forms_socialcontentrequestform_clean_channels", "callee": "get", "is_member_call": true, "source_file": "C:\\Users\\MCN\\Dev\\SDR\\growth_engine_web\\forms.py", "source_location": "L147"}, {"caller_nid": "growth_engine_web_forms_socialcontentrequestform_clean_channels", "callee": "list", "is_member_call": false, "source_file": "C:\\Users\\MCN\\Dev\\SDR\\growth_engine_web\\forms.py", "source_location": "L148"}, {"caller_nid": "growth_engine_web_forms_socialcontentrequestform_clean_notes", "callee": "normalize_whitespace", "is_member_call": false, "source_file": "C:\\Users\\MCN\\Dev\\SDR\\growth_engine_web\\forms.py", "source_location": "L153"}, {"caller_nid": "growth_engine_web_forms_socialcontentrequestform_clean_notes", "callee": "get", "is_member_call": true, "source_file": "C:\\Users\\MCN\\Dev\\SDR\\growth_engine_web\\forms.py", "source_location": "L153"}, {"caller_nid": "growth_engine_web_forms_socialcontentrequestform_clean_delivery_email", "callee": "lower", "is_member_call": true, "source_file": "C:\\Users\\MCN\\Dev\\SDR\\growth_engine_web\\forms.py", "source_location": "L156"}, {"caller_nid": "growth_engine_web_forms_socialcontentrequestform_clean_delivery_email", "callee": "normalize_whitespace", "is_member_call": false, "source_file": "C:\\Users\\MCN\\Dev\\SDR\\growth_engine_web\\forms.py", "source_location": "L156"}, {"caller_nid": "growth_engine_web_forms_socialcontentrequestform_clean_delivery_email", "callee": "get", "is_member_call": true, "source_file": "C:\\Users\\MCN\\Dev\\SDR\\growth_engine_web\\forms.py", "source_location": "L156"}]}